colino/__init__.py
colino/config.py
colino/db.py
colino/digest_manager.py
colino/ingest_manager.py
colino/main.py
colino/oauth_proxy.py
colino/scraper.py
colino/sources/__init__.py
colino/sources/base.py
colino/sources/rss.py
colino/sources/youtube.py
colino/summarize.py
colino-0.1.2.dist-info/METADATA
colino-0.1.2.dist-info/WHEEL
colino-0.1.2.dist-info/entry_points.txt
colino-0.1.2.dist-info/RECORD
